[{
  "_id": {
    "$oid": "67e8191782a0ba877a3faf08"
  },
  "name": "SU",
  "mobile": "1234567890",
  "feasto_points": 100,
  "timestamp": {
    "$date": "2025-03-29T16:00:23.803Z"
  }
},
{
  "_id": {
    "$oid": "67e821f3652c86777cae9a34"
  },
  "name": "NS",
  "mobile": "1234567890",
  "feasto_points": 100,
  "timestamp": {
    "$date": "2025-03-29T16:38:11.654Z"
  }
},
{
  "_id": {
    "$oid": "67e821fc652c86777cae9a35"
  },
  "name": "SS",
  "mobile": "1234567890",
  "feasto_points": 100,
  "timestamp": {
    "$date": "2025-03-29T16:38:20.523Z"
  }
},
{
  "_id": {
    "$oid": "67ec111586708020ec9faea0"
  },
  "name": "MC",
  "mobile": "1234567890",
  "feasto_points": 100,
  "timestamp": {
    "$date": "2025-04-01T16:15:17.777Z"
  }
}]